emews/__about__.py
emews/__init__.py
emews/__main__.py
emews/api/__init__.py
emews/api/env/__init__.py
emews/api/env_key/__init__.py
emews/api/random/__init__.py
emews/api/service/__init__.py
emews/base/__init__.py
emews/base/base_conf.yml
emews/base/client.py
emews/base/config.py
emews/base/env.py
emews/base/env_key.py
emews/base/host.py
emews/base/hostproc.py
emews/base/hub.py
emews/base/hubproc.py
emews/base/node.py
emews/base/random.py
emews/base/service.py
emews/core_emu/__init__.py
emews/core_emu/__main__.py
emews/core_emu/config_services/__init__.py
emews/core_emu/config_services/autossh.py
emews/core_emu/config_services/floodingbot.py
emews/core_emu/config_services/helloworld.py
emews/core_emu/config_services/node/__init__.py
emews/core_emu/config_services/node/services.py
emews/core_emu/config_services/node/templates/emews_node_host.sh
emews/core_emu/config_services/node/templates/emews_node_hub.sh
emews/core_emu/config_services/node/templates/emews_node_monitor.sh
emews/core_emu/config_services/sitecrawler.py
emews/core_emu/config_services/throughput.py
emews/core_emu/example_conf/core.conf
emews/core_emu/legacy_services/__init__.py
emews/core_emu/legacy_services/serv_https.py
emews/core_emu/networks/mews-testbed2.xml
emews/core_emu/networks/udp-flood.xml
emews/core_emu/service_template.py
emews/environments/__init__.py
emews/environments/example/__init__.py
emews/environments/example/environment.py
emews/environments/example/keys.py
emews/environments/web/__init__.py
emews/environments/web/environment.py
emews/environments/web/keys.py
emews/services/__init__.py
emews/services/autossh/__init__.py
emews/services/autossh/default.yml
emews/services/autossh/service.py
emews/services/autossh/ts2-1.yml
emews/services/autossh/ts2-2.yml
emews/services/autossh/ts2-3.yml
emews/services/floodingbot/__init__.py
emews/services/floodingbot/default.yml
emews/services/floodingbot/service.py
emews/services/floodingbot/tcp_bot.yml
emews/services/floodingbot/tcp_bot2.yml
emews-0.9.0.dist-info/LICENSE
emews-0.9.0.dist-info/METADATA
emews-0.9.0.dist-info/WHEEL
emews-0.9.0.dist-info/RECORD
