Metadata-Version: 2.1
Name: emews
Version: 0.9.0
Summary: Network traffic automation and prototyping.
Home-page: https://mews.sv.cmu.edu/research/emews/
License: GPL-3.0-only
Author: Brian Ricks
Author-email: absolutefunk@utdallas.edu
Requires-Python: >=3.8
Classifier: License :: OSI Approved :: GNU General Public License v3 (GPLv3)
Classifier: Operating System :: POSIX :: Linux
Classifier: Programming Language :: Python :: 3
Classifier: Programming Language :: Python :: 3.8
Classifier: Programming Language :: Python :: 3.9
Classifier: Programming Language :: Python :: 3.10
Classifier: Programming Language :: Python :: 3.11
Classifier: Topic :: System :: Logging
Classifier: Topic :: System :: Networking
Requires-Dist: bs4 (>=0.0.1)
Requires-Dist: linuxfd (>=1.4.4)
Requires-Dist: pexpect (>=4.6)
Requires-Dist: psutil (>=5.8)
Requires-Dist: ruamel.yaml (>=0.17)
Requires-Dist: scipy (>=1.5.4)
Requires-Dist: urllib3 (>=1.25.8)
Project-URL: Repository, https://github.com/absolutefunk/emews
